Metadata-Version: 2.1
Name: probability-distribution-functions
Version: 0.1
Summary: Data Distributions: calculates and plots Gaussian & Binomial Distributions from a data file.
Home-page: UNKNOWN
Author: Sheryl Hohman
Author-email: sherylhohman@yahoo.com
License: UNKNOWN
Platform: UNKNOWN
